colabcode/__init__.py
colabcode/code.py
singhtech_colabcode_v1-0.1.0.dist-info/LICENSE
singhtech_colabcode_v1-0.1.0.dist-info/METADATA
singhtech_colabcode_v1-0.1.0.dist-info/WHEEL
singhtech_colabcode_v1-0.1.0.dist-info/top_level.txt
singhtech_colabcode_v1-0.1.0.dist-info/RECORD
