Metadata-Version: 2.1
Name: singhtech-colabcode-v1
Version: 0.1.0
Summary: A package for running VS Code on Colab with ngrok
Home-page: https://github.com/shalusingh-tech/colabcode
Author: Shalu Singh
Author-email: singhtech.10@gmail.com
Classifier: Programming Language :: Python :: 3
Classifier: License :: OSI Approved :: MIT License
Classifier: Operating System :: OS Independent
Requires-Python: >=3.9
License-File: LICENSE
Requires-Dist: pyngrok
Requires-Dist: nest-asyncio
Requires-Dist: uvicorn
